LICENSE
MANIFEST.in
README.rst
setup.cfg
setup.py
paka/__init__.py
paka.cmark.egg-info/PKG-INFO
paka.cmark.egg-info/SOURCES.txt
paka.cmark.egg-info/dependency_links.txt
paka.cmark.egg-info/namespace_packages.txt
paka.cmark.egg-info/not-zip-safe
paka.cmark.egg-info/requires.txt
paka.cmark.egg-info/top_level.txt
paka/cmark/__init__.py
paka/cmark/build_cmark.py
paka/cmark/lowlevel.py
paka/cmark/cmark_src/LICENSE
paka/cmark/cmark_src/blocks.c
paka/cmark/cmark_src/buffer.c
paka/cmark/cmark_src/buffer.h
paka/cmark/cmark_src/case_fold_switch.inc
paka/cmark/cmark_src/chunk.h
paka/cmark/cmark_src/cmark.c
paka/cmark/cmark_src/cmark.h
paka/cmark/cmark_src/cmark_ctype.c
paka/cmark/cmark_src/cmark_ctype.h
paka/cmark/cmark_src/cmark_export.h
paka/cmark/cmark_src/cmark_version.h
paka/cmark/cmark_src/commonmark.c
paka/cmark/cmark_src/config.h
paka/cmark/cmark_src/entities.inc
paka/cmark/cmark_src/houdini.h
paka/cmark/cmark_src/houdini_href_e.c
paka/cmark/cmark_src/houdini_html_e.c
paka/cmark/cmark_src/houdini_html_u.c
paka/cmark/cmark_src/html.c
paka/cmark/cmark_src/inlines.c
paka/cmark/cmark_src/inlines.h
paka/cmark/cmark_src/iterator.c
paka/cmark/cmark_src/iterator.h
paka/cmark/cmark_src/latex.c
paka/cmark/cmark_src/main.c
paka/cmark/cmark_src/man.c
paka/cmark/cmark_src/node.c
paka/cmark/cmark_src/node.h
paka/cmark/cmark_src/parser.h
paka/cmark/cmark_src/references.c
paka/cmark/cmark_src/references.h
paka/cmark/cmark_src/render.c
paka/cmark/cmark_src/render.h
paka/cmark/cmark_src/scanners.c
paka/cmark/cmark_src/scanners.h
paka/cmark/cmark_src/utf8.c
paka/cmark/cmark_src/utf8.h
paka/cmark/cmark_src/xml.c