Metadata-Version: 2.1
Name: paka.cmark
Version: 2.0.0
Summary: Very lightweight CFFI-based Python bindings to cmark library (CommonMark implementation in C).
Home-page: https://github.com/PavloKapyshin/paka.cmark
Author: Pavlo Kapyshin
Author-email: i@93z.org
License: BSD
Keywords: commonmark cmark c ffi
Platform: UNKNOWN
Classifier: Development Status :: 4 - Beta
Classifier: Intended Audience :: Developers
Classifier: License :: OSI Approved :: BSD License
Classifier: Programming Language :: Python :: 2
Classifier: Programming Language :: Python :: 2.7
Classifier: Programming Language :: Python :: 3
Classifier: Programming Language :: Python :: 3.6
Classifier: Programming Language :: Python :: Implementation :: CPython
Classifier: Programming Language :: Python :: Implementation :: PyPy
Provides-Extra: testing
